arsenal/__init__.py
arsenal/alphabet.py
arsenal/assertions.py
arsenal/download.py
arsenal/fsutils.py
arsenal/humanreadable.py
arsenal/integerizer.py
arsenal/iterview.py
arsenal/misc.py
arsenal/nb.py
arsenal/passwords.py
arsenal/profiling.py
arsenal/robust.py
arsenal/sysutil.py
arsenal/terminal.py
arsenal/testing_framework.py
arsenal/timer.py
arsenal/cache/__init__.py
arsenal/cache/lazy.py
arsenal/cache/memoize.py
arsenal/cache/pkl.py
arsenal/datastructures/__init__.py
arsenal/datastructures/bucketqueue.py
arsenal/datastructures/multimap.py
arsenal/datastructures/orderedset.py
arsenal/datastructures/partition_refinement.py
arsenal/datastructures/pdict.py
arsenal/datastructures/unionfind.py
arsenal/datastructures/heap/__init__.py
arsenal/datastructures/heap/heap.c
arsenal/datastructures/heap/heap.cpython-313-i386-linux-musl.so
arsenal/datastructures/heap/heap.pxd
arsenal/datastructures/heap/heap.pyx
arsenal/datastructures/heap/sumheap.c
arsenal/datastructures/heap/sumheap.cpython-313-i386-linux-musl.so
arsenal/datastructures/heap/sumheap.pyx
arsenal/deathrow/__init__.py
arsenal/deathrow/prioritydict.py
arsenal/debug/__init__.py
arsenal/debug/edit.py
arsenal/debug/util.py
arsenal/iterextras/__init__.py
arsenal/iterextras/fair.py
arsenal/iterextras/sort.py
arsenal/iterextras/sorted_intersection.py
arsenal/iterextras/util.py
arsenal/maths/__init__.py
arsenal/maths/bootstrapped.py
arsenal/maths/checkgrad.py
arsenal/maths/cholesky.py
arsenal/maths/compare.py
arsenal/maths/featureselection.py
arsenal/maths/inv.py
arsenal/maths/optimize.py
arsenal/maths/pareto.py
arsenal/maths/rvs.py
arsenal/maths/stepsize.py
arsenal/maths/util.py
arsenal/maths/combinatorics/__init__.py
arsenal/maths/combinatorics/alignments.py
arsenal/maths/combinatorics/basics.py
arsenal/maths/stats/__init__.py
arsenal/maths/stats/corpus_permutation_test.py
arsenal/maths/stats/permutation_test.py
arsenal/nlp/__init__.py
arsenal-3.1.3.dist-info/METADATA
arsenal-3.1.3.dist-info/WHEEL
arsenal-3.1.3.dist-info/top_level.txt
arsenal-3.1.3.dist-info/RECORD
