Metadata-Version: 2.4
Name: arsenal
Version: 3.1.3
Summary: Arsenal of python utilities
Author-email: Tim Vieira <tim.f.vieira@gmail.com>
License: MIT
Classifier: Programming Language :: Python :: 3
Classifier: License :: OSI Approved :: MIT License
Classifier: Operating System :: OS Independent
Requires-Python: >=3.11
Requires-Dist: numpy
Requires-Dist: scipy
Requires-Dist: pandas
Requires-Dist: cython
Requires-Dist: matplotlib
Requires-Dist: gprof2dot
Requires-Dist: graphviz
Requires-Dist: rich
Requires-Dist: path.py
Requires-Dist: IPython
Requires-Dist: tqdm
Requires-Dist: psutil
